LICENSE.txt
MANIFEST.in
README.rst
setup.py
gpsdio_sort/__init__.py
gpsdio_sort/core.py
gpsdio_sort.egg-info/PKG-INFO
gpsdio_sort.egg-info/SOURCES.txt
gpsdio_sort.egg-info/dependency_links.txt
gpsdio_sort.egg-info/entry_points.txt
gpsdio_sort.egg-info/requires.txt
gpsdio_sort.egg-info/top_level.txt
gpsdio_sort.egg-info/zip-safe
tests/test_core.py