Metadata-Version: 1.1
Name: gpsdio-sort
Version: 0.1
Summary: A CLI plugin for `gpsdio` that sorts messages in arbitrarily large files according to an arbitrary set of columns.
Home-page: https://github.com/SkyTruth/gpsdio-sort
Author: Egil Moeller
Author-email: egil@skytruth.org
License: Copyright 2014-2015 SkyTruth
